[
  {
    "팀명": "게임명",
    "1종목": "https://jinsw53.github.io/kingofleague/%EB%8C%80%ED%95%AD%EC%A0%84%20%EA%B4%80%EB%A0%A8/%EB%AA%A8%EC%A3%A0.png",
    "2종목": "https://jinsw53.github.io/kingofleague/%EB%8C%80%ED%95%AD%EC%A0%84%20%EA%B4%80%EB%A0%A8/%EC%95%BC%EC%B0%8C.png",
    "3종목": "https://jinsw53.github.io/kingofleague/%EB%8C%80%ED%95%AD%EC%A0%84%20%EA%B4%80%EB%A0%A8/%EC%B1%8C%EB%A6%B0%EC%A0%80%EC%8A%A4.png",
    "4종목": "https://jinsw53.github.io/kingofleague/%EB%8C%80%ED%95%AD%EC%A0%84%20%EA%B4%80%EB%A0%A8/%EC%A0%9D%EC%8A%A4%EB%8B%98%ED%8A%B8%21.png",
    "5종목": "https://jinsw53.github.io/kingofleague/%EB%8C%80%ED%95%AD%EC%A0%84%20%EA%B4%80%EB%A0%A8/%ED%85%8C%EB%9D%BC%ED%8F%AC%EB%B0%8D%20%EB%A7%88%EC%8A%A4.png",
    "6종목": "https://jinsw53.github.io/kingofleague/%EB%8C%80%ED%95%AD%EC%A0%84%20%EA%B4%80%EB%A0%A8/%ED%94%8C%EB%A6%BD%207.png",
    "7종목": "https://jinsw53.github.io/kingofleague/%EB%8C%80%ED%95%AD%EC%A0%84%20%EA%B4%80%EB%A0%A8/%EC%95%84%ED%81%AC%20%EB%85%B8%EB%B0%94.png",
    "8종목": "https://jinsw53.github.io/kingofleague/%EB%8C%80%ED%95%AD%EC%A0%84%20%EA%B4%80%EB%A0%A8/%EC%8A%A4%ED%94%8C%EB%A0%8C%EB%8D%94.png",
    "9종목": "https://jinsw53.github.io/kingofleague/%EB%8C%80%ED%95%AD%EC%A0%84%20%EA%B4%80%EB%A0%A8/%EB%9F%AD%ED%82%A4%20%EB%84%98%EB%B2%84%EC%8A%A4.png",
    "10종목": "https://jinsw53.github.io/kingofleague/%EB%8C%80%ED%95%AD%EC%A0%84%20%EA%B4%80%EB%A0%A8/%EC%9B%B0%EC%BB%B4%20%ED%88%AC.png",
    "정렬": 1,
    "게임주소": "https://jinsw53.github.io/kingofleague/%EB%8C%80%ED%95%AD%EC%A0%84%20%EA%B4%80%EB%A0%A8/%EB%AA%A8%EC%A3%A0.png"
  },
  {
    "팀명": "토너먼트",
    "1종목": "다인플(5)",
    "2종목": "2인플",
    "3종목": "다인플(3)",
    "4종목": "다인플(5)",
    "5종목": "다인플(5)",
    "6종목": "3-4인플",
    "7종목": "다인플(5)",
    "8종목": "2인플",
    "9종목": "다인플(5)",
    "10종목": "2인플",
    "정렬": 2,
    "게임주소": "https://jinsw53.github.io/kingofleague/%EB%8C%80%ED%95%AD%EC%A0%84%20%EA%B4%80%EB%A0%A8/%EC%95%BC%EC%B0%8C.png"
  },
  {
    "팀명": "방식",
    "1종목": "https://jinsw53.github.io/kingofleague/%EB%8C%80%ED%95%AD%EC%A0%84%20%EA%B4%80%EB%A0%A8/%EB%9D%BC%EC%9A%B4%EB%93%9C%20%EB%A1%9C%EB%B9%88.png",
    "2종목": "https://jinsw53.github.io/kingofleague/%EB%8C%80%ED%95%AD%EC%A0%84%20%EA%B4%80%EB%A0%A8/%EB%9D%BC%EC%9A%B4%EB%93%9C%20%EB%A1%9C%EB%B9%88.png",
    "3종목": "https://jinsw53.github.io/kingofleague/%EB%8C%80%ED%95%AD%EC%A0%84%20%EA%B4%80%EB%A0%A8/%EC%8A%A4%EC%9C%84%EC%8A%A4%20%EC%8B%9C%EC%8A%A4%ED%85%9C.png",
    "4종목": "https://jinsw53.github.io/kingofleague/%EB%8C%80%ED%95%AD%EC%A0%84%20%EA%B4%80%EB%A0%A8/%EC%8A%A4%EC%9C%84%EC%8A%A4%20%EC%8B%9C%EC%8A%A4%ED%85%9C.png",
    "5종목": "https://jinsw53.github.io/kingofleague/%EB%8C%80%ED%95%AD%EC%A0%84%20%EA%B4%80%EB%A0%A8/%EC%8A%A4%EC%9C%84%EC%8A%A4%20%EC%8B%9C%EC%8A%A4%ED%85%9C.png",
    "6종목": "https://jinsw53.github.io/kingofleague/%EB%8C%80%ED%95%AD%EC%A0%84%20%EA%B4%80%EB%A0%A8/%EB%A9%80%ED%8B%B0%20%EC%97%98%EB%A6%AC%EB%AF%B8%EB%84%A4%EC%9D%B4%EC%85%98.png",
    "7종목": "https://jinsw53.github.io/kingofleague/%EB%8C%80%ED%95%AD%EC%A0%84%20%EA%B4%80%EB%A0%A8/%EC%8A%A4%EC%9C%84%EC%8A%A4%20%EC%8B%9C%EC%8A%A4%ED%85%9C.png",
    "8종목": "https://jinsw53.github.io/kingofleague/%EB%8C%80%ED%95%AD%EC%A0%84%20%EA%B4%80%EB%A0%A8/%EC%8B%B1%EA%B8%80%20%EC%97%98%EB%A6%AC%EB%AF%B8%EB%84%A4%EC%9D%B4%EC%85%98.png",
    "9종목": "https://jinsw53.github.io/kingofleague/%EB%8C%80%ED%95%AD%EC%A0%84%20%EA%B4%80%EB%A0%A8/%EC%8A%A4%EC%9C%84%EC%8A%A4%20%EC%8B%9C%EC%8A%A4%ED%85%9C.png",
    "10종목": "https://jinsw53.github.io/kingofleague/%EB%8C%80%ED%95%AD%EC%A0%84%20%EA%B4%80%EB%A0%A8/%EC%8B%B1%EA%B8%80%20%EC%97%98%EB%A6%AC%EB%AF%B8%EB%84%A4%EC%9D%B4%EC%85%98.png",
    "정렬": 3,
    "게임주소": "https://jinsw53.github.io/kingofleague/%EB%8C%80%ED%95%AD%EC%A0%84%20%EA%B4%80%EB%A0%A8/%EC%B1%8C%EB%A6%B0%EC%A0%80%EC%8A%A4.png"
  },
  {
    "이미지 주소": "https://jinsw53.github.io/kingofleague/G%EB%BF%94%201%EC%8A%B9.png\n",
    "팀명": "G뿔",
    "1종목": "Tina113",
    "2종목": "Tina113",
    "3종목": "jinsw53",
    "4종목": "mg lee",
    "5종목": "tobyyun",
    "6종목": "tobyyun",
    "7종목": "mg lee",
    "8종목": "jinsw53",
    "정렬": 4,
    "게임주소": "https://jinsw53.github.io/kingofleague/%EB%8C%80%ED%95%AD%EC%A0%84%20%EA%B4%80%EB%A0%A8/%EC%A0%9D%EC%8A%A4%EB%8B%98%ED%8A%B8%21.png"
  },
  {
    "이미지 주소": "https://jinsw53.github.io/kingofleague/%EB%B3%B4%EB%93%9C%ED%8C%90%EC%9D%98_%EB%AC%B8%EC%96%B4%EB%93%A4%203%EC%8A%B9.png",
    "팀명": "보드판의 문어들",
    "1종목": "voyagermomo",
    "2종목": "moonyo",
    "3종목": "happiness1106",
    "4종목": "voyagermomo",
    "5종목": "illgongiee",
    "6종목": "illgongiee",
    "7종목": "moonyo",
    "8종목": "happiness1106",
    "정렬": 5,
    "게임주소": "https://jinsw53.github.io/kingofleague/%EB%8C%80%ED%95%AD%EC%A0%84%20%EA%B4%80%EB%A0%A8/%ED%85%8C%EB%9D%BC%ED%8F%AC%EB%B0%8D%20%EB%A7%88%EC%8A%A4.png"
  },
  {
    "이미지 주소": "https://jinsw53.github.io/kingofleague/%EB%B6%80%EC%9E%90-%EB%8D%94%EC%8A%A4%ED%8B%B4%EB%B0%A4.png",
    "팀명": "부자",
    "정렬": 6,
    "게임주소": "https://jinsw53.github.io/kingofleague/%EB%8C%80%ED%95%AD%EC%A0%84%20%EA%B4%80%EB%A0%A8/%ED%94%8C%EB%A6%BD%207.png"
  },
  {
    "이미지 주소": "https://jinsw53.github.io/kingofleague/%EB%8B%AC%EC%9D%84_%EB%B3%B4%EB%8B%A4.png",
    "팀명": "달을_보다",
    "정렬": 7,
    "게임주소": "https://jinsw53.github.io/kingofleague/%EB%8C%80%ED%95%AD%EC%A0%84%20%EA%B4%80%EB%A0%A8/%EC%95%84%ED%81%AC%20%EB%85%B8%EB%B0%94.png"
  },
  {
    "이미지 주소": "https://jinsw53.github.io/kingofleague/%EA%B0%95%EC%95%8C%EB%A6%AC.png",
    "팀명": "강알리",
    "정렬": 8,
    "게임주소": "https://jinsw53.github.io/kingofleague/%EB%8C%80%ED%95%AD%EC%A0%84%20%EA%B4%80%EB%A0%A8/%EC%8A%A4%ED%94%8C%EB%A0%8C%EB%8D%94.png"
  },
  {
    "이미지 주소": "https://jinsw53.github.io/kingofleague/%ED%83%9C%EA%B7%B9-%EB%8F%99%ED%95%B4.png",
    "팀명": "태극",
    "정렬": 9,
    "게임주소": "https://jinsw53.github.io/kingofleague/%EB%8C%80%ED%95%AD%EC%A0%84%20%EA%B4%80%EB%A0%A8/%EB%9F%AD%ED%82%A4%20%EB%84%98%EB%B2%84%EC%8A%A4.png"
  },
  {
    "게임주소": "https://jinsw53.github.io/kingofleague/%EB%8C%80%ED%95%AD%EC%A0%84%20%EA%B4%80%EB%A0%A8/%EC%9B%B0%EC%BB%B4%20%ED%88%AC.png"
  }
]